pygritbx/__init__.py
pygritbx/bevelGear.py
pygritbx/component.py
pygritbx/fatigueLimitCorrectorFactors.py
pygritbx/force.py
pygritbx/gear.py
pygritbx/gearMesh.py
pygritbx/geometricStressRaiser.py
pygritbx/helicalGear.py
pygritbx/inputMotor.py
pygritbx/makima2dInterpolator.py
pygritbx/material.py
pygritbx/motor.py
pygritbx/notchSensitivity.py
pygritbx/oil.py
pygritbx/shaft.py
pygritbx/shaftProfile.py
pygritbx/shaftSection.py
pygritbx/support.py
pygritbx/torque.py
pygritbx-1.1.2.dist-info/licenses/LICENSE
pygritbx-1.1.2.dist-info/METADATA
pygritbx-1.1.2.dist-info/WHEEL
pygritbx-1.1.2.dist-info/top_level.txt
pygritbx-1.1.2.dist-info/RECORD
