Metadata-Version: 2.4
Name: pygritbx
Version: 1.1.2
Summary: Python-based Gearbox Reliability and Integrity Tool
Home-page: https://github.com/Rmhuneineh/pygritbx
Author: Ragheed Huneineh
Author-email: ragheedmhuneineh@outlook.com
License: MIT
Classifier: License :: OSI Approved :: MIT License
Classifier: Programming Language :: Python :: 3.11
Classifier: Operating System :: OS Independent
Classifier: Intended Audience :: Education
Classifier: Natural Language :: English
Classifier: Topic :: Scientific/Engineering
Requires-Python: >= 3.11.5
License-File: LICENSE
Requires-Dist: numpy>=2.2.4
Requires-Dist: scipy>=1.15.2
Requires-Dist: matplotlib>=3.10.1
Provides-Extra: dev
Requires-Dist: twine>=6.1.0; extra == "dev"
Dynamic: author
Dynamic: author-email
Dynamic: classifier
Dynamic: description
Dynamic: description-content-type
Dynamic: home-page
Dynamic: license
Dynamic: license-file
Dynamic: provides-extra
Dynamic: requires-dist
Dynamic: requires-python
Dynamic: summary
